{"id_art": "06bc23293776d2a6ee2ab35b304e758d", "title": "Koh-Lanta aux iles Fidji : la saison la plus chere ", "newspaper": "LeFigaro", "author": ["Emilie Geffray"], "date_publi": "2017-09-01", "content": "Des eaux bleues, une vegetation luxuriante, des plages de sable blanc, des recifs coralliens colores, des paysages a couper le souffle. Pour la nouvelle saison de Koh-Lanta , TF1 et Adventure Line Productions ont opte pour les paradisiaques iles Fidji. Vingt-sept heures de voyage sont necessaires pour parcourir les 16.532 kilometres qui les separent de la France. Pas de quoi effrayer Denis Brogniart, bien au contraire. <<C'est un endroit exceptionnel, l'un des coins les plus desertiques que j'ai rencontres! Il faut resituer le contexte: deja, les iles Fidji sont perdues au milieu du Pacifique, mais, nous, nous etions dans ce que j'appelle la Lozere des Fidji!>>, souligne avec humour l'animateur. Un lieu tellement vierge et recule qu'il a fallu a ALP construire de quoi loger la cent cinquantaine de personnes presentes sur place, installer des canalisations d'eau et d'electricite, etablir des routes, transformer des conteneurs en logement, le tout avec l'aide de la population locale. <<Il n'y avait qu'un tout petit hotel de dix-huit chambres et aucune infrastructure sur lesquelles s'appuyer. En fin de compte, on a fait du BTP>>, commente Alexia Laroche-Joubert, la productrice, precisant que c'est la saison qui a coute le plus cher.Mais pourquoi avoir entrepris de tels travaux? <<A l'origine, on avait trouve un autre endroit, mais on a eu un souci (le passage du cyclone Winston a cause enormement de degats sur la premiere ile, NDR) . On s'est donc retrouves a deux mois et demi du debut du tournage sans lieu ou travailler, poursuit-elle. J'ai pris la decision d'envoyer en urgence mes equipes pour sillonner les iles Fidji, et un de mes collaborateurs m'a finalement appelee pour dire qu'il avait trouve le plus bel endroit que Koh-Lanta ait connu. TF1 n'etait pas au courant, je leur ai dit la semaine derniere.>>Cote nouveautes, la production s'est encore une fois creuse les meninges pour ravir les plus de 6 millions de telespectateurs. Pour la troisieme fois dans l'histoire du jeu, des candidats ages de 19 a 29 ans vont affronter ceux de 30 a 57 ans. <<Ca m'interessait de voir, avec les a priori qu'on peut avoir, comment les uns et les autres allaient gerer a la fois la survie et les epreuves. Des le premier episode, alors qu'en general les jeunes sont tout feu tout flamme, desorganises, etc., ils vont se reveler tres surprenants et aller a l'encontre de toutes les idees recues que l'on peut avoir>>, ajoute Alexia Laroche-Joubert. Un choc des generations qui ne durera pas puisque deux nouvelles equipes seront composees au bout de dix jours d'aventure. <<On voulait vraiment perturber les candidats et les telespectateurs. Et je trouvais interessant de jouer avec cette opposition au debut et de redistribuer les cartes>>, poursuit la productrice. Ainsi, les coequipiers du debut vont devenir des adversaires et inversement. Andre, Caroline, Delphine, Fabian, Magalie, Manu, Marguerite, Marine, Marta, Marvyn, Maxime, Mel, Melanie, Romain, Sandrine, Sebastien, Theotime, Thomas, Tiffany et Tugdual sont les vingt nouveaux aventuriers a tenter l'aventure Koh-Lanta. Originaires de France, de Belgique, de Suisse et de Monaco, les apprentis Robinson vont, des les premieres minutes, etre confrontes aux difficultes. Et, pour eviter tout abandon volontaire, vecu comme un echec par la production, cette derniere <<a porte un regard tout particulier sur la selection des candidats>>. <<On a choisi des gens extremement determines, qui ont reellement envie d'y aller et qui ont de vrais enjeux personnels suffisamment forts pour resister a la difficulte de la survie>>, souligne Alexia Laroche-Joubert, qui a beaucoup d'affection pour le gerant d'un food truck vosgien. <<J'ai beaucoup de tendresse pour Theotime, qui est un personnage incroyable et va vous etonner. Ce gamin qui semble \"inapte de chez inapte\" avec ce cote pieds nickeles, c'est finalement lui qui va reussir a faire pas mal de choses. C'est une vraie decouverte.>>Enfin, pour intensifier un peu plus le cote strategique deja present dans Koh-Lanta, la production a mis en place l'<<ile du paradis perdu>>. <<Pour la premiere fois dans l'histoire de Koh-Lanta, un rouge et un jaune vont devoir s'allier et rester ensemble longtemps>>, explique la productrice. A chaque epreuve de confort, un membre de l'equipe rouge et un de l'equipe jaune vont se retrouver sur ce fameux ilot, ou sont caches onze coffres, contenant chacun ou plusieurs elements strategiques, comme un collier d'immunite scinde en deux, par exemple. De quoi offrir une multitude de possibilites. <<C'est une saison qui a beaucoup d'elements strategiques>>, confirme Alexia Laroche-Joubert.", "theme": "cyclone"}