{"id_art": "bbe71cd5c7a0c38cb7c4af737fe9677a", "title": "Apres l'ouragan Irma, Saint-Martin reprend le chemin de l'ecole", "newspaper": "LeFigaro", "author": ["Amandine Ascensio"], "date_publi": "2017-09-13", "content": "Saint-Martin <<A peine une semaine apres la catastrophe, on ne peut pas encore dire quels seront les etablissements scolaires qui rouvriront en premier, ni meme faire un chiffrage du cout des travaux>>, indique Jean-Michel Blanquer, le ministre de l'Education nationale, arrive mardi avec Emmanuel Macron a Saint-Martin, l'ile francaise devastee par l'ouragan Irma. Selon lui, l'activite dans les ecoles reprendra selon les cas de figure, apres un diagnostic pousse de chaque batiment et des travaux necessaires. En effet, certains etablissements ont ete totalement detruits, d'autres le sont peu. <<On fera du cas par cas, ecole par ecole, college par college et lycee par lycee>>, indique le ministre. Des tentes gonflables assureront l'interim des batiments, et les cours seront assures par les enseignants qui auront choisi de rester, ou d'autres, arrives de GuadeloupeQuelques familles ...", "theme": "cyclone"}