{"id_art": "8f2657cf276741315a9ed4bf165cf139", "title": "\nPhilippines: Manille noyee par la mousson, 53 morts et transports paralyses", "newspaper": "LePoint", "author": [], "date_publi": "2012-08-07", "content": "Les pluies de mousson qui se sont abattues ces derniers jours sur les Philippines ont noye la moitie de la capitale Manille, paralyse les transports, les administrations et les ecoles, et fait 53 morts a travers le pays, selon un bilan encore provisoire annonce mardi. Au moins 20.000 personnes ont du abandonner leurs maisons, les plus pauvres vivant a proximite des egouts et des cours d'eau en crue dans les bidonvilles de la metropole de 15 millions d'habitants etant les plus vulnerables. Les inondations ont coupe les routes et les ecoles, la Bourse, les bureaux et les administrations etaient quasiment deserts mardi. L'armee a ete appelee en renfort pour assurer les evacuations et secourir les habitants refugies dans les etages ou sur les toits. \"Au moins 50% du grand Manille est inonde. De fortes pluies sont attendues dans les prochaines 24 heures. Les inondations vont s'aggraver\", a declare a l'AFP Jean Navarez, de l'agence meteorologique des Philippines. Les pluies de mousson et le typhon Saola qui a balaye le nord du pays la semaine derniere ont fait au total 53 morts et plus de 268.000 deplaces, selon le dernier bilan officiel qui ne prend pas en compte le deluge de la derniere nuit. Une vingtaine de typhons frappent les Philippines chaque annee pendant la saison (ete et automne). ", "theme": "typhon"}