{"id_art": "1540ca38febf8de5d947d06c6ed29804", "title": "Orages et inondations : l'Herault a nouveau en vigilance orange", "newspaper": "LePoint", "author": ["Source AFP"], "date_publi": "2016-10-22", "content": "Meteo-France appelle a la vigilance en raison d'un \"risque de pluies intenses\" dans le departement, de samedi minuit jusqu'a dimanche 8 heures. Une semaine apres un episode de fortes pluies dans l'Herault, Meteo-France a de nouveau place le departement du sud de la France en vigilance orange pour la nuit de samedi 22 a dimanche 23 octobre, de minuit a 8 heures du matin, a cause d'orages et de risques d'inondations, annonce un bulletin publie samedi. Meteo-France evoque une << situation pluvieuse et orageuse necessitant une vigilance particuliere >> et un << risque de pluies intenses concernant les memes zones pendant plusieurs heures >>, principalement << sur le littoral et le proche interieur de l'Herault >>. Les pluies vont commencer samedi en fin de journee et << s'intensifieront et pourront devenir orageuses >> en seconde partie de nuit, precise-t-il. << De forts cumuls pourront donc etre observes. On attend des quantites de l'ordre de 80 a 150 mm en 3 a 6 heures de temps >>, ajoute le bulletin. Des inondations de caves et de sous-sols peuvent se produire tres rapidement, et << les conditions de circulation routiere peuvent etre rendues difficiles >>, avertit Meteo-France. La semaine derniere, les pluies de forte intensite avaient declenche une vigilance rouge dans l'Herault. Les intemperies n'avaient cependant pas engendre de degats majeurs. ", "theme": "innondation"}